{
    "PC": [],
    "LC": [],
    "addedPC": [],
    "addedLC": [
      {
        "linesArray": [
          {
            "p1": {
              "x": 782,
              "y": 801,
              "type": null
            },
            "p2": {
              "x": 168,
              "y": 201,
              "type": null
            }
          },
          {
            "p1": {
              "x": 882,
              "y": 342,
              "type": null
            },
            "p2": {
              "x": 93,
              "y": 506,
              "type": null
            }
          },
          {
            "p1": {
              "x": 369,
              "y": 933,
              "type": null
            },
            "p2": {
              "x": 242,
              "y": 98,
              "type": null
            }
          },
          {
            "p1": {
              "x": 857,
              "y": 592,
              "type": null
            },
            "p2": {
              "x": 172,
              "y": 673,
              "type": null
            }
          },
          {
            "p1": {
              "x": 641,
              "y": 858,
              "type": null
            },
            "p2": {
              "x": 197,
              "y": 320,
              "type": null
            }
          },
          {
            "p1": {
              "x": 709,
              "y": 536,
              "type": null
            },
            "p2": {
              "x": 157,
              "y": 733,
              "type": null
            }
          },
          {
            "p1": {
              "x": 826,
              "y": 732,
              "type": null
            },
            "p2": {
              "x": 180,
              "y": 497,
              "type": null
            }
          },
  {
            "p1": {
              "x": 578,
              "y": 276,
              "type": null
            },
            "p2": {
              "x": 298,
              "y": 928,
              "type": null
            }
          }
        ],
        "lineFirstPoint": {
          "x": 826,
          "y": 732,
          "type": null
        }
      }
    ]
  }
  