{
  "PC": [],
  "LC": [],
  "addedPC": [],
  "addedLC": [],
  "shapes": [
    {
      "PC": {
        "pointsArray": [
          {
            "x": 676,
            "y": 279,
            "type": null,
            "payload": [
              0,
              [
                5,
                0
              ],
              null
            ]
          },
          {
            "x": 903,
            "y": 537,
            "type": null,
            "payload": [
              0,
              [
                0,
                1
              ],
              4
            ]
          },
          {
            "x": 719,
            "y": 673,
            "type": null,
            "payload": [
              0,
              [
                1,
                2
              ],
              2
            ]
          },
          {
            "x": 658,
            "y": 566,
            "type": null,
            "payload": [
              0,
              [
                2,
                3
              ],
              1
            ]
          },
          {
            "x": 720,
            "y": 510,
            "type": null,
            "payload": [
              0,
              [
                3,
                4
              ],
              3
            ]
          },
          {
            "x": 622,
            "y": 329,
            "type": null,
            "payload": [
              0,
              [
                4,
                5
              ],
              0
            ]
          }
        ],
        "type": null
      },
      "LC": {
        "linesArray": [
          {
            "p1": {
              "x": 676,
              "y": 279,
              "type": null,
              "payload": [
                0,
                [
                  5,
                  0
                ],
                null
              ]
            },
            "p2": {
              "x": 903,
              "y": 537,
              "type": null,
              "payload": [
                0,
                [
                  0,
                  1
                ],
                4
              ]
            }
          },
          {
            "p1": {
              "x": 903,
              "y": 537,
              "type": null,
              "payload": [
                0,
                [
                  0,
                  1
                ],
                4
              ]
            },
            "p2": {
              "x": 719,
              "y": 673,
              "type": null,
              "payload": [
                0,
                [
                  1,
                  2
                ],
                2
              ]
            }
          },
          {
            "p1": {
              "x": 719,
              "y": 673,
              "type": null,
              "payload": [
                0,
                [
                  1,
                  2
                ],
                2
              ]
            },
            "p2": {
              "x": 658,
              "y": 566,
              "type": null,
              "payload": [
                0,
                [
                  2,
                  3
                ],
                1
              ]
            }
          },
          {
            "p1": {
              "x": 658,
              "y": 566,
              "type": null,
              "payload": [
                0,
                [
                  2,
                  3
                ],
                1
              ]
            },
            "p2": {
              "x": 720,
              "y": 510,
              "type": null,
              "payload": [
                0,
                [
                  3,
                  4
                ],
                3
              ]
            }
          },
          {
            "p1": {
              "x": 720,
              "y": 510,
              "type": null,
              "payload": [
                0,
                [
                  3,
                  4
                ],
                3
              ]
            },
            "p2": {
              "x": 622,
              "y": 329,
              "type": null,
              "payload": [
                0,
                [
                  4,
                  5
                ],
                0
              ]
            }
          },
          {
            "p1": {
              "x": 622,
              "y": 329,
              "type": null,
              "payload": [
                0,
                [
                  4,
                  5
                ],
                0
              ]
            },
            "p2": {
              "x": 676,
              "y": 279,
              "type": null,
              "payload": [
                0,
                [
                  5,
                  0
                ],
                null
              ]
            }
          }
        ]
      },
      "type": null,
      "index": 0,
      "tmp": [
        0,
        [
          4,
          0
        ],
        null
      ]
    }
  ]
}
